{
  "NameSpace": {
    "Name": "d7JXcoup",
    "ID": 0,
    "UIDSeed": 100009
  },
  "FileSpaces": [
    {
      "Path": "EditorGenLib.fcc",
      "Symbol": {
        "Components": [
          {
            "Name": "Mob",
            "ID": 100000,
            "Props": [
              {
                "ID": 100005,
                "Name": "MobName"
              },
              {
                "ID": 100001,
                "Name": "MaxHP"
              },
              {
                "ID": 100002,
                "Name": "HP"
              },
              {
                "ID": 100003,
                "Name": "WalkSpeed"
              },
              {
                "ID": 100004,
                "Name": "Damage"
              },
              {
                "ID": 100007,
                "Name": "StatusDic"
              },
              {
                "ID": 100006,
                "Name": "CurrTarget"
              },
              {
                "ID": 100008,
                "Name": "LastHitPlayer"
              }
            ]
          }
        ],
        "Events": [],
        "Graphs": [
          {
            "ID": "EDITOR_GEN_RESOURCE_REGISTERATION_ID2oacb87rc",
            "Name": "Res",
            "Props": [
              {
                "ID": "EDITOR_GEN_Resourceui",
                "Name": "UI"
              },
              {
                "ID": "EDITOR_GEN_Resourcescene",
                "Name": "Scene"
              },
              {
                "ID": "EDITOR_GEN_Resourceprefab",
                "Name": "Prefab"
              },
              {
                "ID": "EDITOR_GEN_Resourcefcg",
                "Name": "FCG"
              },
              {
                "ID": "EDITOR_GEN_Resourceeca",
                "Name": "ECA"
              },
              {
                "ID": "EDITOR_GEN_Resourcesprite",
                "Name": "Sprite"
              },
              {
                "ID": "EDITOR_GEN_Resourceeffect",
                "Name": "Effect"
              },
              {
                "ID": "EDITOR_GEN_Resourcesound",
                "Name": "Sound"
              },
              {
                "ID": "EDITOR_GEN_Resourceitem",
                "Name": "Item"
              },
              {
                "ID": "EDITOR_GEN_Resourcelevelobject",
                "Name": "LevelObject"
              },
              {
                "ID": "EDITOR_GEN_Resourcecloth",
                "Name": "Cloth"
              },
              {
                "ID": "EDITOR_GEN_Resourceweaponskin",
                "Name": "WeaponSkin"
              },
              {
                "ID": "EDITOR_GEN_Resourcevehicleskin",
                "Name": "VehicleSkin"
              },
              {
                "ID": "EDITOR_GEN_Resourceemote",
                "Name": "Emote"
              },
              {
                "ID": "EDITOR_GEN_Resourcecsv",
                "Name": "CSV"
              },
              {
                "ID": "EDITOR_GEN_Resourceinternalhud",
                "Name": "InternalHud"
              },
              {
                "ID": "EDITOR_GEN_Resourcetexture",
                "Name": "Texture"
              },
              {
                "ID": "EDITOR_GEN_Resourcemesh",
                "Name": "Mesh"
              },
              {
                "ID": "EDITOR_GEN_Resourcematerial",
                "Name": "Material"
              },
              {
                "ID": "EDITOR_GEN_Resourceanimationcontroller",
                "Name": "AnimationController"
              },
              {
                "ID": "EDITOR_GEN_Resourceparticles",
                "Name": "Particles"
              },
              {
                "ID": "EDITOR_GEN_Resourceplayerdata",
                "Name": "PlayerData"
              },
              {
                "ID": "EDITOR_GEN_Resourcebehaviortree",
                "Name": "BehaviorTree"
              },
              {
                "ID": "EDITOR_GEN_Resourceperformance",
                "Name": "Performance"
              },
              {
                "ID": "Editor_Gen_Resource_UI_Skill",
                "Name": "Skill"
              },
              {
                "ID": "Editor_Gen_Resource_UI_DeBug",
                "Name": "DeBug"
              }
            ],
            "Funcs": []
          }
        ],
        "Enums": [
          {
            "ID": -673569,
            "Name": "EResFCG",
            "Items": [
              {
                "Name": "C_HitBox",
                "Value": "d7JXcoupLi9Bc3NldHMvU2NyaXB0cy9DX0hpdEJveC5mY2c="
              }
            ]
          },
          {
            "ID": -629121,
            "Name": "EResECA",
            "Items": []
          },
          {
            "ID": -478560,
            "Name": "EResPrefab",
            "Items": [
              {
                "Name": "NormalZombie",
                "Value": "/1/DoDDweTl"
              },
              {
                "Name": "HitBox_Zombie_Body",
                "Value": "/2/FbiodFjI"
              },
              {
                "Name": "HitBox_Zombie_Head",
                "Value": "/3/FbiodFjI"
              },
              {
                "Name": "HitBox_Zombie_LeftArm",
                "Value": "/4/FbiodFjI"
              },
              {
                "Name": "HitBox_Zombie_Leg",
                "Value": "/5/FbiodFjI"
              },
              {
                "Name": "HitBox_Zombie_RightArm",
                "Value": "/6/FbiodFjI"
              }
            ]
          },
          {
            "ID": -940135,
            "Name": "EResSprite",
            "Items": []
          },
          {
            "ID": -365949,
            "Name": "EResTexture",
            "Items": []
          },
          {
            "ID": -213929,
            "Name": "EResEffect",
            "Items": []
          },
          {
            "ID": -691745,
            "Name": "EResSound",
            "Items": []
          },
          {
            "ID": -849629,
            "Name": "EResItem",
            "Items": [
              {
                "Name": "Gun_AK47",
                "Value": 6
              }
            ]
          },
          {
            "ID": -861261,
            "Name": "EResLevelObject",
            "Items": []
          },
          {
            "ID": -548881,
            "Name": "EResCloth",
            "Items": []
          },
          {
            "ID": -855414,
            "Name": "EResWeaponSkin",
            "Items": []
          },
          {
            "ID": -543641,
            "Name": "EResVehicleSkin",
            "Items": []
          },
          {
            "ID": -946111,
            "Name": "EResEmote",
            "Items": []
          },
          {
            "ID": -96591,
            "Name": "EResCSV",
            "Items": [
              {
                "Name": "LevelConfig",
                "Value": "d7JXcoup.qvynabkauac-mhctomfo-m27x1ilqm9q"
              },
              {
                "Name": "MonsterInfo",
                "Value": "d7JXcoup.s1ys4w63d4-mhctomfr-gkrblrpqng"
              }
            ]
          },
          {
            "ID": -140846,
            "Name": "EResInternalHud",
            "Items": []
          },
          {
            "ID": -540624,
            "Name": "EResMesh",
            "Items": []
          },
          {
            "ID": -357249,
            "Name": "EResMaterial",
            "Items": []
          },
          {
            "ID": -218214,
            "Name": "EResAnimationController",
            "Items": []
          },
          {
            "ID": -808012,
            "Name": "EResParticles",
            "Items": []
          },
          {
            "ID": -533849,
            "Name": "EResPlayerData",
            "Items": []
          },
          {
            "ID": -552974,
            "Name": "EResBehaviorTree",
            "Items": []
          },
          {
            "ID": -655855,
            "Name": "EResPerformance",
            "Items": []
          },
          {
            "ID": -888864,
            "Name": "EResScene",
            "Items": []
          },
          {
            "ID": -5465,
            "Name": "EResUI",
            "Items": [
              {
                "Name": "Skill",
                "Value": "/7/jsEtqWBw"
              },
              {
                "Name": "DeBug",
                "Value": "/8/I1NmYoLv"
              }
            ]
          },
          {
            "ID": -767459,
            "Name": "EResUISkill",
            "Items": [
              {
                "Name": "JoyStickFillAmount",
                "Value": 1
              },
              {
                "Name": "",
                "Value": 2
              }
            ]
          },
          {
            "ID": -273675,
            "Name": "EResUIDeBug",
            "Items": []
          },
          {
            "Name": "EResKeyUI",
            "ID": 314391,
            "Items": []
          },
          {
            "Name": "EResKeyScene",
            "ID": 397023,
            "Items": []
          },
          {
            "Name": "EResKeyPrefab",
            "ID": 212236,
            "Items": []
          },
          {
            "Name": "EResKeyFCG",
            "ID": 198029,
            "Items": []
          },
          {
            "Name": "EResKeyECA",
            "ID": 952958,
            "Items": []
          },
          {
            "Name": "EResKeySprite",
            "ID": 814843,
            "Items": []
          },
          {
            "Name": "EResKeyEffect",
            "ID": 355949,
            "Items": []
          },
          {
            "Name": "EResKeySound",
            "ID": 662212,
            "Items": []
          },
          {
            "Name": "EResKeyItem",
            "ID": 176470,
            "Items": []
          },
          {
            "Name": "EResKeyLevelObject",
            "ID": 397314,
            "Items": []
          },
          {
            "Name": "EResKeyCloth",
            "ID": 210523,
            "Items": []
          },
          {
            "Name": "EResKeyWeaponSkin",
            "ID": 460243,
            "Items": []
          },
          {
            "Name": "EResKeyVehicleSkin",
            "ID": 769247,
            "Items": []
          },
          {
            "Name": "EResKeyEmote",
            "ID": 148954,
            "Items": []
          },
          {
            "Name": "EResKeyCSV",
            "ID": 149148,
            "Items": []
          },
          {
            "Name": "EResKeyInternalHud",
            "ID": 593009,
            "Items": []
          },
          {
            "Name": "EResKeyTexture",
            "ID": 456827,
            "Items": []
          },
          {
            "Name": "EResKeyMesh",
            "ID": 369512,
            "Items": []
          },
          {
            "Name": "EResKeyMaterial",
            "ID": 817889,
            "Items": []
          },
          {
            "Name": "EResKeyAnimationController",
            "ID": 735610,
            "Items": []
          },
          {
            "Name": "EResKeyParticles",
            "ID": 429949,
            "Items": []
          },
          {
            "Name": "EResKeyPlayerData",
            "ID": 841477,
            "Items": []
          },
          {
            "Name": "EResKeyBehaviorTree",
            "ID": 617040,
            "Items": []
          },
          {
            "Name": "EResKeyPerformance",
            "ID": 519395,
            "Items": []
          },
          {
            "Name": "EResKeySkill",
            "ID": 54702,
            "Items": []
          },
          {
            "Name": "EResKeyDeBug",
            "ID": 656454,
            "Items": []
          },
          {
            "Name": "EPhase",
            "ID": 200001,
            "Items": []
          }
        ]
      }
    },
    {
      "Path": "wehss29x.fcc",
      "Symbol": {
        "Components": [],
        "Events": [],
        "Graphs": [],
        "Enums": [
          {
            "Name": "EPhase",
            "ID": 200001,
            "Items": []
          }
        ]
      }
    },
    {
      "Path": "BA9iBjOL.fcc",
      "Symbol": {
        "Components": [],
        "Events": [],
        "Graphs": [
          {
            "ID": "BA9iBjOL.whgog58btr-lx1724pg-3h0scyd2o43",
            "Name": "__BA9iBjOLzooSpawn6Point6Auto6Closerneca__",
            "Props": [],
            "Funcs": []
          }
        ],
        "Enums": [
          {
            "Name": "EPhase",
            "ID": 200001,
            "Items": []
          }
        ]
      }
    },
    {
      "Path": "NnIxhh2E.fcc",
      "Symbol": {
        "Components": [],
        "Events": [],
        "Graphs": [],
        "Enums": [
          {
            "Name": "EPhase",
            "ID": 200001,
            "Items": []
          }
        ]
      }
    }
  ]
}